gwaves/__init__.py
gwaves/gwaves_.py
gwaves-0.0.3.1.dist-info/LICENSE
gwaves-0.0.3.1.dist-info/METADATA
gwaves-0.0.3.1.dist-info/WHEEL
gwaves-0.0.3.1.dist-info/top_level.txt
gwaves-0.0.3.1.dist-info/RECORD
